ligninkmc/__init__.py
ligninkmc/_version.py
ligninkmc/analysis.py
ligninkmc/create_lignin.py
ligninkmc/event.py
ligninkmc/kmc_common.py
ligninkmc/kmc_functions.py
ligninkmc/monomer.py
ligninkmc/visualization.py
ligninkmc-0.2.2.dist-info/LICENSE
ligninkmc-0.2.2.dist-info/METADATA
ligninkmc-0.2.2.dist-info/WHEEL
ligninkmc-0.2.2.dist-info/entry_points.txt
ligninkmc-0.2.2.dist-info/top_level.txt
ligninkmc-0.2.2.dist-info/RECORD
